cqlpy/__init__.py
cqlpy/_internal/__init__.py
cqlpy/_internal/context/context.py
cqlpy/_internal/context/cql_valueset_provider.py
cqlpy/_internal/context/fhir/fhir_cql_type.py
cqlpy/_internal/context/fhir/r4/default_property.py
cqlpy/_internal/context/fhir/r4/map.py
cqlpy/_internal/context/fhir/r4/model.py
cqlpy/_internal/context/parameter_provider.py
cqlpy/_internal/context/resource_query.py
cqlpy/_internal/context/type_factory.py
cqlpy/_internal/exceptions.py
cqlpy/_internal/logger.py
cqlpy/_internal/operators/aggregate/count.py
cqlpy/_internal/operators/arithmetic/max_value.py
cqlpy/_internal/operators/arithmetic/min_value.py
cqlpy/_internal/operators/clinical/any_in_valueset.py
cqlpy/_internal/operators/clinical/calculate_age_at.py
cqlpy/_internal/operators/clinical/in_valueset.py
cqlpy/_internal/operators/comparison/equal.py
cqlpy/_internal/operators/comparison/equivalent.py
cqlpy/_internal/operators/comparison/greater.py
cqlpy/_internal/operators/comparison/greater_or_equal.py
cqlpy/_internal/operators/comparison/in_list.py
cqlpy/_internal/operators/comparison/less.py
cqlpy/_internal/operators/comparison/less_or_equal.py
cqlpy/_internal/operators/comparison/not_equal.py
cqlpy/_internal/operators/cql_in.py
cqlpy/_internal/operators/date_time/add.py
cqlpy/_internal/operators/date_time/after.py
cqlpy/_internal/operators/date_time/before.py
cqlpy/_internal/operators/date_time/date_time_precision.py
cqlpy/_internal/operators/date_time/difference_between.py
cqlpy/_internal/operators/date_time/duration_between.py
cqlpy/_internal/operators/date_time/same_or_before.py
cqlpy/_internal/operators/date_time/subtract.py
cqlpy/_internal/operators/interval/collapse.py
cqlpy/_internal/operators/interval/end.py
cqlpy/_internal/operators/interval/in_interval.py
cqlpy/_internal/operators/interval/included_in.py
cqlpy/_internal/operators/interval/overlaps.py
cqlpy/_internal/operators/interval/start.py
cqlpy/_internal/operators/list/distinct.py
cqlpy-0.3.1.dist-info/LICENSE
cqlpy-0.3.1.dist-info/METADATA
cqlpy-0.3.1.dist-info/WHEEL
cqlpy-0.3.1.dist-info/RECORD
