Metadata-Version: 2.3
Name: cqlpy
Version: 0.3.1
Summary: Tooling to execute CQL-like Python against FHIR resources.
License: MIT
Author: John Wyderko
Author-email: john@careevolution.com
Requires-Python: >=3.9
Classifier: License :: OSI Approved :: MIT License
Classifier: Programming Language :: Python :: 3
Classifier: Programming Language :: Python :: 3.9
Classifier: Programming Language :: Python :: 3.10
Classifier: Programming Language :: Python :: 3.11
Classifier: Programming Language :: Python :: 3.12
Classifier: Programming Language :: Python :: 3.13
Requires-Dist: requests (>=2.31.0,<3.0.0)
